clippings_cli/__init__.py
clippings_cli/clippings_service/__init__.py
clippings_cli/clippings_service/format_handlers/__init__.py
clippings_cli/clippings_service/format_handlers/excel_handlers.py
clippings_cli/clippings_service/format_handlers/json_handlers.py
clippings_cli/clippings_service/parsers.py
clippings_cli/clippings_service/service.py
clippings_cli/clippings_service/validators.py
clippings_cli/commands/__init__.py
clippings_cli/commands/convert.py
clippings_cli/entrypoint.py
clippings_cli-1.0.2.dist-info/METADATA
clippings_cli-1.0.2.dist-info/WHEEL
clippings_cli-1.0.2.dist-info/entry_points.txt
clippings_cli-1.0.2.dist-info/RECORD
